junospyez_ossh_server/__init__.py
junospyez_ossh_server/about.py
junospyez_ossh_server/dmi.py
junospyez_ossh_server/log.py
junospyez_ossh_server/ossh_server.py
junospyez_ossh_server-0.1.2.dist-info/LICENSE
junospyez_ossh_server-0.1.2.dist-info/METADATA
junospyez_ossh_server-0.1.2.dist-info/WHEEL
junospyez_ossh_server-0.1.2.dist-info/top_level.txt
junospyez_ossh_server-0.1.2.dist-info/RECORD
