Metadata-Version: 2.1
Name: junospyez-ossh-server
Version: 0.1.2
Summary: Outbound SSH for use with Junos systems
Home-page: https://github.com/jeremyschulman/junospyez-ossh-server
Author: Jeremy Schulman
Author-email: jschulman@juniper.net
License: UNKNOWN
Platform: UNKNOWN
Classifier: Programming Language :: Python :: 3
Classifier: License :: OSI Approved :: MIT License
Classifier: Operating System :: OS Independent
Requires-Dist: junos-eznc (>=2.2.0)
